ssm_tunneler/__init__.py
ssm_tunneler/ssm_tunneler.py
ssm_tunneler-0.0.2.dist-info/LICENSE
ssm_tunneler-0.0.2.dist-info/METADATA
ssm_tunneler-0.0.2.dist-info/WHEEL
ssm_tunneler-0.0.2.dist-info/top_level.txt
ssm_tunneler-0.0.2.dist-info/RECORD
