Metadata-Version: 2.1
Name: ssm_tunneler
Version: 0.0.2
Summary: ssm_tunneler es una biblioteca diseñada para simplificar la apertura de túneles SSH a través de AWS Systems Manager (SSM). Este paquete permite a los desarrolladores y administradores de sistemas establecer conexiones seguras a instancias EC2 en entornos de AWS sin necesidad de exponer públicamente las instancias.
Author-email: Fernando Nicolás Carrillo López <pandasoncode@gmail.com>
License: MIT
Project-URL: Homepage, https://github.com/pandasoncode/aws-ssm-tunneler
Requires-Python: >=3.12.2
License-File: LICENSE
Requires-Dist: boto3
